request_filters/__init__.py
request_filters/utils.py
request_filters/decorators/__init__.py
request_filters/decorators/ip_check.py
request_filters/middlewares/__init__.py
request_filters/middlewares/ip_check.py
django_request_filters-0.0.4.dist-info/METADATA
django_request_filters-0.0.4.dist-info/WHEEL
django_request_filters-0.0.4.dist-info/licenses/LICENSE
django_request_filters-0.0.4.dist-info/RECORD
