Metadata-Version: 2.1
Name: django-request-filters
Version: 0.0.4
Summary: Block the users those are using VPN, Proxy, TOR or Relay.
Project-URL: Homepage, https://pypi.org/project/django-request-filters
Project-URL: Source code, https://github.com/Samiddha99/django-request-filters
Project-URL: Bug Tracker, https://github.com/Samiddha99/django-request-filters/issues
Author-email: Samiddha Chakrabarti <samiddha99@protonmail.com>
Maintainer-email: Samiddha Chakrabarti <samiddha99@protonmail.com>
License-Expression: MIT
License-File: LICENSE
Keywords: Proxy,Relay,TOR,VPN,cybersecurity,djabgo security,django,python,security
Classifier: Development Status :: 5 - Production/Stable
Classifier: Environment :: Other Environment
Classifier: Framework :: Django :: 4.2
Classifier: Intended Audience :: Developers
Classifier: License :: OSI Approved :: MIT License
Classifier: Natural Language :: English
Classifier: Operating System :: OS Independent
Classifier: Programming Language :: Python :: 3
Classifier: Topic :: Utilities
Requires-Python: >=3.10
Requires-Dist: django
Requires-Dist: django-ipware
Requires-Dist: requests
